ColumnSplitFill/__init__.py
ColumnSplitFill/main.py
ColumnSplitFill-0.3.dist-info/METADATA
ColumnSplitFill-0.3.dist-info/WHEEL
ColumnSplitFill-0.3.dist-info/entry_points.txt
ColumnSplitFill-0.3.dist-info/top_level.txt
ColumnSplitFill-0.3.dist-info/RECORD
